claii/__init__.py
claii/cli.py
claii-0.1.0.dist-info/METADATA
claii-0.1.0.dist-info/WHEEL
claii-0.1.0.dist-info/entry_points.txt
claii-0.1.0.dist-info/top_level.txt
claii-0.1.0.dist-info/RECORD
