Metadata-Version: 2.1
Name: claii
Version: 0.1.0
Summary: claii - Command Line AI Interface
Home-page: https://github.com/wensheng/claii
Author: Wensheng Wang
Author-email: wenshengwang@gmail.com
License: Apache License, Version 2.0
Project-URL: Issues, https://github.com/wensheng/claii/issues
Requires-Python: >=3.6
Requires-Dist: click
Requires-Dist: openai
Requires-Dist: chromadb
Requires-Dist: python-dotenv
